snd4onnx/__init__.py
snd4onnx/__main__.py
snd4onnx/onnx_remove_node.py
snd4onnx-1.1.6.dist-info/LICENSE
snd4onnx-1.1.6.dist-info/METADATA
snd4onnx-1.1.6.dist-info/WHEEL
snd4onnx-1.1.6.dist-info/entry_points.txt
snd4onnx-1.1.6.dist-info/top_level.txt
snd4onnx-1.1.6.dist-info/RECORD
