Metadata-Version: 2.1
Name: snd4onnx
Version: 1.1.6
Summary: Simple node deletion tool for onnx.
Home-page: https://github.com/PINTO0309/snd4onnx
Author: Katsuya Hyodo
Author-email: rmsdh122@yahoo.co.jp
License: MIT License
Platform: linux
Platform: unix
Requires-Python: >=3.6
License-File: LICENSE
